duoname/__init__.py
duoname/__main__.py
duoname-0.0.1.dist-info/LICENSE
duoname-0.0.1.dist-info/METADATA
duoname-0.0.1.dist-info/WHEEL
duoname-0.0.1.dist-info/entry_points.txt
duoname-0.0.1.dist-info/top_level.txt
duoname-0.0.1.dist-info/RECORD
