Metadata-Version: 2.1
Name: duoname
Version: 0.0.1
Summary: Random string <adjective>-<noun>. Useful for user-friendly name generation.
Author-email: Mike Kroutikov <mkroutikov@innodata.com>
License: MIT License
Project-URL: Homepage, https://github.com/innodatalabs/duoname
Project-URL: Documentation, https://github.com/innodatalabs/duoname
Project-URL: Repository, https://github.com/innodatalabs/duoname
Keywords: random name
Classifier: Development Status :: 3 - Alpha
Classifier: Intended Audience :: Developers
Classifier: License :: OSI Approved :: MIT License
Classifier: Programming Language :: Python :: 3
Classifier: Programming Language :: Python :: 3.10
Classifier: Programming Language :: Python :: 3.11
Classifier: Programming Language :: Python :: 3.12
Requires-Python: >=3.10
License-File: LICENSE
